KAFY/__init__.py
KAFY/commandsParser.py
KAFY/constraintsClass.py
KAFY/kafyShell.py
KAFY/mainPipeline.py
KAFY/modelsLoader.py
KAFY/modelsRepo.py
KAFY/partioningClass.py
KAFY/utilFunctions.py
KAFY/assets/h3_clusters.pkl
KAFY/assets/h3_kmeans_clustering_all_models_precise.pkl
KAFY/assets/projectLocation.txt
KAFYTraj-0.2.7.dist-info/LICENSE
KAFYTraj-0.2.7.dist-info/METADATA
KAFYTraj-0.2.7.dist-info/WHEEL
KAFYTraj-0.2.7.dist-info/entry_points.txt
KAFYTraj-0.2.7.dist-info/top_level.txt
KAFYTraj-0.2.7.dist-info/RECORD
