Metadata-Version: 2.1
Name: KAFYTraj
Version: 0.2.7
Summary: This library includes an extensible system for building various trajectory operations.
Author: Youssef Hussein
Classifier: Programming Language :: Python :: 3
Classifier: Programming Language :: Python :: 3.6
Classifier: Programming Language :: Python :: 3.7
Classifier: Programming Language :: Python :: 3.8
Classifier: Programming Language :: Python :: 3.9
Classifier: License :: OSI Approved :: MIT License
Classifier: Operating System :: OS Independent
Requires-Python: >=3.6
License-File: LICENSE
Requires-Dist: h3
Requires-Dist: transformers
Requires-Dist: datasets
Requires-Dist: tokenizers
Requires-Dist: transformers[torch]
Requires-Dist: numpy
Requires-Dist: pyarrow<16.0.0,>=14.0.1
